botatecalculator/__init__.py
botatecalculator/calculator.py
botatecalculator-0.0.1.dist-info/LICENCE.txt
botatecalculator-0.0.1.dist-info/METADATA
botatecalculator-0.0.1.dist-info/WHEEL
botatecalculator-0.0.1.dist-info/top_level.txt
botatecalculator-0.0.1.dist-info/RECORD
