Metadata-Version: 2.1
Name: botatecalculator
Version: 0.0.1
Summary: A very basic calculator
Home-page: 
Author: CTO Botate
Author-email: botate@armada.mil.ec
License: MIT
Keywords: calculator
Classifier: Development Status :: 5 - Production/Stable
Classifier: Intended Audience :: Education
Classifier: Operating System :: Microsoft :: Windows :: Windows 10
Classifier: License :: OSI Approved :: MIT License
Classifier: Programming Language :: Python :: 3
License-File: LICENCE.txt
